{"cameraMode":{"drawMode":0,"name":"Shaded","section":"Shading Mode"},"sceneLighting":true,"audioPlay":false,"sceneViewState":{"showFog":true,"showMaterialUpdate":false,"showSkybox":true,"showFlares":true,"showImageEffects":true,"showParticleSystems":true,"showVisualEffectGraphs":true,"m_FxEnabled":true},"in2DMode":false,"pivot":{"x":18.115215301513673,"y":-17.585758209228517,"z":1.4702068567276},"rotation":{"x":-0.19991658627986909,"y":-0.5193639993667603,"z":0.12644267082214356,"w":-0.8211549520492554},"size":25.859424591064454,"orthographic":false}